botstory/__init__.py
botstory/chat.py
botstory/chat_test.py
botstory/matchers.py
botstory/story.py
botstory/story_test.py
botstory/version.txt
botstory/ast/__init__.py
botstory/ast/callable.py
botstory/ast/callable_test.py
botstory/ast/common.py
botstory/ast/forking.py
botstory/ast/forking_test.py
botstory/ast/library.py
botstory/ast/library_test.py
botstory/ast/loop.py
botstory/ast/loop_test.py
botstory/ast/parser.py
botstory/ast/processor.py
botstory/ast/stack_utils.py
botstory/ast/users.py
botstory/ast/story_context/__init__.py
botstory/ast/story_context/reducers.py
botstory/ast/story_context/reducers_test.py
botstory/ast/story_context/story_context_test.py
botstory/di/__init__.py
botstory/di/desciption.py
botstory/di/inject.py
botstory/di/inject_test.py
botstory/di/injector_service.py
botstory/di/injector_service_test.py
botstory/di/parser.py
botstory/di/parser_test.py
botstory/integrations/__init__.py
botstory/integrations/aiohttp/__init__.py
botstory/integrations/aiohttp/aiohttp.py
botstory/integrations/aiohttp/aiohttp_test.py
botstory/integrations/commonhttp/__init__.py
botstory/integrations/commonhttp/errors.py
botstory/integrations/commonhttp/statuses.py
botstory/integrations/fb/__init__.py
botstory/integrations/fb/messenger.py
botstory/integrations/fb/messenger_test.py
botstory/integrations/fb/validate.py
botstory/integrations/fb/validate_test.py
botstory/integrations/ga/__init__.py
botstory/integrations/ga/tracker.py
botstory/integrations/ga/tracker_test.py
botstory/integrations/ga/universal_analytics/__init__.py
botstory/integrations/ga/universal_analytics/fake_analytics.py
botstory/integrations/ga/universal_analytics/tracker.py
botstory/integrations/ga/universal_analytics/tracker_test.py
botstory/integrations/mockdb/__init__.py
botstory/integrations/mockdb/db.py
botstory/integrations/mockdb/db_test.py
botstory/integrations/mockhttp/__init__.py
botstory/integrations/mockhttp/mockhttp.py
botstory-0.1.5.dist-info/DESCRIPTION.rst
botstory-0.1.5.dist-info/METADATA
botstory-0.1.5.dist-info/RECORD
botstory-0.1.5.dist-info/WHEEL
botstory-0.1.5.dist-info/metadata.json
botstory-0.1.5.dist-info/top_level.txt
