Metadata-Version: 2.0
Name: botstory
Version: 0.1.5
Summary: Async framework for bots
Home-page: https://github.com/botstory/bot-story
Author: Eugene Krevenets
Author-email: ievegenii.krevenets@gmail.com
License: MIT
Download-URL: https://github.com/botstory/bot-story/tarball/0.1.5
Keywords: bot,ai,nlp,asyncio
Platform: UNKNOWN
Classifier: Development Status :: 1 - Planning
Classifier: Intended Audience :: Developers
Classifier: Topic :: Communications :: Chat
Classifier: Programming Language :: Python :: 3.5
Requires-Dist: aiohttp (==2.0.7)
Requires-Dist: motor (==1.1)
Requires-Dist: yarl (==0.10.0)
